alibabacloud_rds20140815/__init__.py
alibabacloud_rds20140815/client.py
alibabacloud_rds20140815/models/__init__.py
alibabacloud_rds20140815/models/_accept_rcinquired_system_event_request.py
alibabacloud_rds20140815/models/_accept_rcinquired_system_event_response.py
alibabacloud_rds20140815/models/_accept_rcinquired_system_event_response_body.py
alibabacloud_rds20140815/models/_activate_migration_target_instance_request.py
alibabacloud_rds20140815/models/_activate_migration_target_instance_response.py
alibabacloud_rds20140815/models/_activate_migration_target_instance_response_body.py
alibabacloud_rds20140815/models/_add_tags_to_resource_request.py
alibabacloud_rds20140815/models/_add_tags_to_resource_response.py
alibabacloud_rds20140815/models/_add_tags_to_resource_response_body.py
alibabacloud_rds20140815/models/_allocate_instance_public_connection_request.py
alibabacloud_rds20140815/models/_allocate_instance_public_connection_response.py
alibabacloud_rds20140815/models/_allocate_instance_public_connection_response_body.py
alibabacloud_rds20140815/models/_allocate_read_write_splitting_connection_request.py
alibabacloud_rds20140815/models/_allocate_read_write_splitting_connection_response.py
alibabacloud_rds20140815/models/_allocate_read_write_splitting_connection_response_body.py
alibabacloud_rds20140815/models/_associate_eip_address_with_rcinstance_request.py
alibabacloud_rds20140815/models/_associate_eip_address_with_rcinstance_response.py
alibabacloud_rds20140815/models/_associate_eip_address_with_rcinstance_response_body.py
alibabacloud_rds20140815/models/_attach_rcdisk_request.py
alibabacloud_rds20140815/models/_attach_rcdisk_response.py
alibabacloud_rds20140815/models/_attach_rcdisk_response_body.py
alibabacloud_rds20140815/models/_attach_rcinstances_request.py
alibabacloud_rds20140815/models/_attach_rcinstances_response.py
alibabacloud_rds20140815/models/_attach_rcinstances_response_body.py
alibabacloud_rds20140815-15.1.1.dist-info/LICENSE
alibabacloud_rds20140815-15.1.1.dist-info/METADATA
alibabacloud_rds20140815-15.1.1.dist-info/WHEEL
alibabacloud_rds20140815-15.1.1.dist-info/top_level.txt
alibabacloud_rds20140815-15.1.1.dist-info/RECORD
